image_builder-0.2.0.dist-info/METADATA
image_builder-0.2.0.dist-info/RECORD
image_builder-0.2.0.dist-info/WHEEL
image_builder-0.2.0.dist-info/top_level.txt
shortest_image_builder/__init__.py
shortest_image_builder/docker_handler.py
shortest_image_builder/image_builder.py
shortest_image_builder/stdockerfile.py
shortest_image_builder/utils.py
