Metadata-Version: 2.1
Name: image-builder
Version: 0.2.0
Summary: UNKNOWN
Home-page: UNKNOWN
Author: UNKNOWN
Author-email: UNKNOWN
License: UNKNOWN
Platform: UNKNOWN
Requires-Dist: shortesttrack-tools (<0.2,>=0.1.8)
